leedsx/__init__.py
ltrhieu1994-0.2.dist-info/DESCRIPTION.rst
ltrhieu1994-0.2.dist-info/METADATA
ltrhieu1994-0.2.dist-info/RECORD
ltrhieu1994-0.2.dist-info/WHEEL
ltrhieu1994-0.2.dist-info/metadata.json
ltrhieu1994-0.2.dist-info/top_level.txt
