Metadata-Version: 2.0
Name: ltrhieu1994
Version: 0.2
Summary: Hello World
Home-page: UNKNOWN
Author: Hieu Le
Author-email: ltrhieu1994@gmail.com
License: BKU
Platform: UNKNOWN
